{
    "top._rn60_rec_dataH_graphrename_579": [
        [
            "",
            "'d0_graphrename_580"
        ]
    ],
    "'d0_graphrename_580": [],
    "top._rn61_rec_dataH_graphrename_581": [
        [
            "",
            "top_rec_dataH_temp"
        ]
    ],
    "top_rec_dataH_temp": [],
    "top.iRECEIVER._rn43_next_state_graphrename_582": [
        [
            "",
            "top.iRECEIVER.state_graphrename_749"
        ]
    ],
    "top.iRECEIVER.state_graphrename_749": [
        [
            "",
            "Branch_graphrename_750"
        ]
    ],
    "Branch_graphrename_750": [
        [
            "FALSE",
            "top_iRECEIVER_next_state"
        ],
        [
            "COND",
            "Unot_graphrename_751"
        ],
        [
            "TRUE",
            "3'd1_graphrename_752"
        ]
    ],
    "top.iRECEIVER._rn44_cntr_resetH_graphrename_583": [
        [
            "",
            "1'd1_graphrename_584"
        ]
    ],
    "1'd1_graphrename_584": [],
    "top.iRECEIVER._rn45_shiftH_graphrename_585": [
        [
            "",
            "1'd0_graphrename_586"
        ]
    ],
    "1'd0_graphrename_586": [],
    "top.iRECEIVER._rn46_countH_graphrename_587": [
        [
            "",
            "1'd0_graphrename_588"
        ]
    ],
    "1'd0_graphrename_588": [],
    "top.iRECEIVER._rn47_rstCountH_graphrename_589": [
        [
            "",
            "1'd0_graphrename_590"
        ]
    ],
    "1'd0_graphrename_590": [],
    "top.iRECEIVER._rn48_rec_readyInH_graphrename_591": [
        [
            "",
            "1'd0_graphrename_592"
        ]
    ],
    "1'd0_graphrename_592": [],
    "top.iRECEIVER._rn49_next_state_graphrename_593": [
        [
            "",
            "3'd2_graphrename_594"
        ]
    ],
    "3'd2_graphrename_594": [],
    "top.iRECEIVER._rn50_rstCountH_graphrename_595": [
        [
            "",
            "1'd1_graphrename_596"
        ]
    ],
    "1'd1_graphrename_596": [],
    "top.iRECEIVER._rn51_rec_readyInH_graphrename_597": [
        [
            "",
            "1'd1_graphrename_598"
        ]
    ],
    "1'd1_graphrename_598": [],
    "top.iRECEIVER._rn52_next_state_graphrename_599": [
        [
            "",
            "3'd3_graphrename_600"
        ]
    ],
    "3'd3_graphrename_600": [],
    "top.iRECEIVER._rn53_next_state_graphrename_601": [
        [
            "",
            "3'd1_graphrename_602"
        ]
    ],
    "3'd1_graphrename_602": [],
    "top.iRECEIVER._rn54_cntr_resetH_graphrename_603": [
        [
            "",
            "1'd0_graphrename_604"
        ]
    ],
    "1'd0_graphrename_604": [],
    "top.iRECEIVER._rn55_next_state_graphrename_605": [
        [
            "",
            "3'd1_graphrename_606"
        ]
    ],
    "3'd1_graphrename_606": [],
    "top.iRECEIVER._rn56_rec_readyInH_graphrename_607": [
        [
            "",
            "1'd1_graphrename_608"
        ]
    ],
    "1'd1_graphrename_608": [],
    "top.iRECEIVER._rn57_shiftH_graphrename_609": [
        [
            "",
            "1'd1_graphrename_610"
        ]
    ],
    "1'd1_graphrename_610": [],
    "top.iRECEIVER._rn58_countH_graphrename_611": [
        [
            "",
            "1'd1_graphrename_612"
        ]
    ],
    "1'd1_graphrename_612": [],
    "top.iRECEIVER._rn59_cntr_resetH_graphrename_613": [
        [
            "",
            "1'd0_graphrename_614"
        ]
    ],
    "1'd0_graphrename_614": [],
    "top.iRECEIVER.bitCell_cntrH_graphrename_615": [
        [
            "",
            "Branch_graphrename_616"
        ]
    ],
    "Branch_graphrename_616": [
        [
            "COND",
            "Unot_graphrename_617"
        ],
        [
            "TRUE",
            "'d0_graphrename_618"
        ],
        [
            "FALSE",
            "Branch_graphrename_619"
        ]
    ],
    "Unot_graphrename_617": [
        [
            "",
            "top_iRECEIVER_sys_rst_l"
        ]
    ],
    "'d0_graphrename_618": [],
    "Branch_graphrename_619": [
        [
            "COND",
            "top_iRECEIVER_cntr_resetH"
        ],
        [
            "TRUE",
            "'d0_graphrename_620"
        ],
        [
            "FALSE",
            "Plus_graphrename_621"
        ]
    ],
    "top_iRECEIVER_sys_rst_l": [],
    "top_iRECEIVER_cntr_resetH": [],
    "'d0_graphrename_620": [],
    "Plus_graphrename_621": [
        [
            "",
            "top_iRECEIVER_bitCell_cntrH"
        ],
        [
            "",
            "'d1_graphrename_622"
        ]
    ],
    "top_iRECEIVER_bitCell_cntrH": [],
    "'d1_graphrename_622": [],
    "top.iRECEIVER.cntr_resetH_graphrename_623": [
        [
            "",
            "Branch_graphrename_624"
        ]
    ],
    "Branch_graphrename_624": [
        [
            "TRUE",
            "top_iRECEIVER_cntr_resetH"
        ],
        [
            "COND",
            "Eq_graphrename_625"
        ],
        [
            "FALSE",
            "Branch_graphrename_627"
        ]
    ],
    "Eq_graphrename_625": [
        [
            "",
            "top.iRECEIVER.state_graphrename_749"
        ],
        [
            "",
            "3'd1_graphrename_626"
        ]
    ],
    "Branch_graphrename_627": [
        [
            "COND",
            "Eq_graphrename_628"
        ],
        [
            "TRUE",
            "Branch_graphrename_630"
        ],
        [
            "FALSE",
            "Branch_graphrename_633"
        ]
    ],
    "3'd1_graphrename_626": [],
    "Eq_graphrename_628": [
        [
            "",
            "top.iRECEIVER.state_graphrename_749"
        ],
        [
            "",
            "3'd2_graphrename_629"
        ]
    ],
    "Branch_graphrename_630": [
        [
            "COND",
            "Eq_graphrename_631"
        ],
        [
            "TRUE",
            "top_iRECEIVER__rn44_cntr_resetH"
        ],
        [
            "FALSE",
            "top_iRECEIVER__rn54_cntr_resetH"
        ]
    ],
    "Branch_graphrename_633": [
        [
            "FALSE",
            "top_iRECEIVER_cntr_resetH"
        ],
        [
            "COND",
            "Eq_graphrename_634"
        ],
        [
            "TRUE",
            "Branch_graphrename_636"
        ]
    ],
    "3'd2_graphrename_629": [],
    "Eq_graphrename_631": [
        [
            "",
            "top_iRECEIVER_bitCell_cntrH"
        ],
        [
            "",
            "4'd4_graphrename_632"
        ]
    ],
    "top_iRECEIVER__rn44_cntr_resetH": [],
    "top_iRECEIVER__rn54_cntr_resetH": [],
    "Eq_graphrename_634": [
        [
            "",
            "top.iRECEIVER.state_graphrename_749"
        ],
        [
            "",
            "3'd3_graphrename_635"
        ]
    ],
    "Branch_graphrename_636": [
        [
            "TRUE",
            "top_iRECEIVER_cntr_resetH"
        ],
        [
            "COND",
            "Eq_graphrename_637"
        ],
        [
            "FALSE",
            "top_iRECEIVER__rn59_cntr_resetH"
        ]
    ],
    "4'd4_graphrename_632": [],
    "3'd3_graphrename_635": [],
    "Eq_graphrename_637": [
        [
            "",
            "top_iRECEIVER_bitCell_cntrH"
        ],
        [
            "",
            "4'd14_graphrename_638"
        ]
    ],
    "top_iRECEIVER__rn59_cntr_resetH": [],
    "4'd14_graphrename_638": [],
    "top.iRECEIVER.countH_graphrename_639": [
        [
            "",
            "Branch_graphrename_640"
        ]
    ],
    "Branch_graphrename_640": [
        [
            "COND",
            "Eq_graphrename_641"
        ],
        [
            "FALSE",
            "Branch_graphrename_643"
        ]
    ],
    "Eq_graphrename_641": [
        [
            "",
            "top.iRECEIVER.state_graphrename_749"
        ],
        [
            "",
            "3'd1_graphrename_642"
        ]
    ],
    "Branch_graphrename_643": [
        [
            "COND",
            "Eq_graphrename_644"
        ],
        [
            "FALSE",
            "Branch_graphrename_646"
        ]
    ],
    "3'd1_graphrename_642": [],
    "Eq_graphrename_644": [
        [
            "",
            "top.iRECEIVER.state_graphrename_749"
        ],
        [
            "",
            "3'd2_graphrename_645"
        ]
    ],
    "Branch_graphrename_646": [
        [
            "COND",
            "Eq_graphrename_647"
        ],
        [
            "TRUE",
            "Branch_graphrename_649"
        ]
    ],
    "3'd2_graphrename_645": [],
    "Eq_graphrename_647": [
        [
            "",
            "top.iRECEIVER.state_graphrename_749"
        ],
        [
            "",
            "3'd3_graphrename_648"
        ]
    ],
    "Branch_graphrename_649": [
        [
            "COND",
            "Eq_graphrename_650"
        ],
        [
            "TRUE",
            "Branch_graphrename_652"
        ]
    ],
    "3'd3_graphrename_648": [],
    "Eq_graphrename_650": [
        [
            "",
            "top_iRECEIVER_bitCell_cntrH"
        ],
        [
            "",
            "4'd14_graphrename_651"
        ]
    ],
    "Branch_graphrename_652": [
        [
            "COND",
            "Eq_graphrename_653"
        ],
        [
            "TRUE",
            "top_iRECEIVER__rn46_countH"
        ],
        [
            "FALSE",
            "top_iRECEIVER__rn58_countH"
        ]
    ],
    "4'd14_graphrename_651": [],
    "Eq_graphrename_653": [
        [
            "",
            "top_iRECEIVER_recd_bitCntrH"
        ],
        [
            "",
            "'d8_graphrename_654"
        ]
    ],
    "top_iRECEIVER__rn46_countH": [],
    "top_iRECEIVER__rn58_countH": [],
    "top_iRECEIVER_recd_bitCntrH": [],
    "'d8_graphrename_654": [],
    "top.iRECEIVER.next_state_graphrename_655": [
        [
            "",
            "Branch_graphrename_656"
        ]
    ],
    "Branch_graphrename_656": [
        [
            "COND",
            "Eq_graphrename_657"
        ],
        [
            "TRUE",
            "Branch_graphrename_659"
        ],
        [
            "FALSE",
            "Branch_graphrename_661"
        ]
    ],
    "Eq_graphrename_657": [
        [
            "",
            "top.iRECEIVER.state_graphrename_749"
        ],
        [
            "",
            "3'd1_graphrename_658"
        ]
    ],
    "Branch_graphrename_659": [
        [
            "COND",
            "Unot_graphrename_660"
        ],
        [
            "TRUE",
            "top_iRECEIVER__rn49_next_state"
        ],
        [
            "FALSE",
            "top_iRECEIVER__rn43_next_state"
        ]
    ],
    "Branch_graphrename_661": [
        [
            "COND",
            "Eq_graphrename_662"
        ],
        [
            "TRUE",
            "Branch_graphrename_664"
        ],
        [
            "FALSE",
            "Branch_graphrename_669"
        ]
    ],
    "3'd1_graphrename_658": [],
    "Unot_graphrename_660": [
        [
            "",
            "top_iRECEIVER_rec_datH"
        ]
    ],
    "top_iRECEIVER__rn49_next_state": [],
    "top_iRECEIVER__rn43_next_state": [],
    "Eq_graphrename_662": [
        [
            "",
            "top.iRECEIVER.state_graphrename_749"
        ],
        [
            "",
            "3'd2_graphrename_663"
        ]
    ],
    "Branch_graphrename_664": [
        [
            "COND",
            "Eq_graphrename_665"
        ],
        [
            "TRUE",
            "Branch_graphrename_667"
        ],
        [
            "FALSE",
            "top_iRECEIVER_next_state"
        ]
    ],
    "Branch_graphrename_669": [
        [
            "FALSE",
            "top_iRECEIVER_next_state"
        ],
        [
            "COND",
            "Eq_graphrename_670"
        ],
        [
            "TRUE",
            "Branch_graphrename_672"
        ]
    ],
    "top_iRECEIVER_rec_datH": [],
    "3'd2_graphrename_663": [],
    "Eq_graphrename_665": [
        [
            "",
            "top_iRECEIVER_bitCell_cntrH"
        ],
        [
            "",
            "4'd4_graphrename_666"
        ]
    ],
    "Branch_graphrename_667": [
        [
            "COND",
            "Unot_graphrename_668"
        ],
        [
            "TRUE",
            "top_iRECEIVER__rn52_next_state"
        ],
        [
            "FALSE",
            "top_iRECEIVER__rn53_next_state"
        ]
    ],
    "top_iRECEIVER_next_state": [],
    "Eq_graphrename_670": [
        [
            "",
            "top.iRECEIVER.state_graphrename_749"
        ],
        [
            "",
            "3'd3_graphrename_671"
        ]
    ],
    "Branch_graphrename_672": [
        [
            "FALSE",
            "top_iRECEIVER_next_state"
        ],
        [
            "COND",
            "Eq_graphrename_673"
        ],
        [
            "TRUE",
            "Branch_graphrename_675"
        ]
    ],
    "4'd4_graphrename_666": [],
    "Unot_graphrename_668": [
        [
            "",
            "top_iRECEIVER_rec_datH"
        ]
    ],
    "top_iRECEIVER__rn52_next_state": [],
    "top_iRECEIVER__rn53_next_state": [],
    "3'd3_graphrename_671": [],
    "Eq_graphrename_673": [
        [
            "",
            "top_iRECEIVER_bitCell_cntrH"
        ],
        [
            "",
            "4'd14_graphrename_674"
        ]
    ],
    "Branch_graphrename_675": [
        [
            "FALSE",
            "top_iRECEIVER_next_state"
        ],
        [
            "COND",
            "Eq_graphrename_676"
        ],
        [
            "TRUE",
            "top_iRECEIVER__rn55_next_state"
        ]
    ],
    "4'd14_graphrename_674": [],
    "Eq_graphrename_676": [
        [
            "",
            "top_iRECEIVER_recd_bitCntrH"
        ],
        [
            "",
            "'d8_graphrename_677"
        ]
    ],
    "top_iRECEIVER__rn55_next_state": [],
    "'d8_graphrename_677": [],
    "top.iRECEIVER.par_dataH_graphrename_678": [
        [
            "",
            "Branch_graphrename_679"
        ]
    ],
    "Branch_graphrename_679": [
        [
            "COND",
            "Unot_graphrename_680"
        ],
        [
            "TRUE",
            "8'd0_graphrename_681"
        ],
        [
            "FALSE",
            "Branch_graphrename_682"
        ]
    ],
    "Unot_graphrename_680": [
        [
            "",
            "top_iRECEIVER_sys_rst_l"
        ]
    ],
    "8'd0_graphrename_681": [],
    "Branch_graphrename_682": [
        [
            "TRUE",
            "Concat_graphrename_683"
        ],
        [
            "FALSE",
            "top_iRECEIVER_par_dataH"
        ],
        [
            "",
            "top.iRECEIVER.shiftH_graphrename_733"
        ]
    ],
    "Concat_graphrename_683": [
        [
            "",
            "top_iRECEIVER_rec_datH"
        ],
        [
            "",
            "PartSelect_graphrename_684"
        ]
    ],
    "top_iRECEIVER_par_dataH": [],
    "top.iRECEIVER.shiftH_graphrename_733": [
        [
            "",
            "Branch_graphrename_734"
        ]
    ],
    "PartSelect_graphrename_684": [
        [
            "VAR",
            "top_iRECEIVER_par_dataH"
        ],
        [
            "MSB",
            "'d7_graphrename_685"
        ],
        [
            "LSB",
            "'d1_graphrename_686"
        ]
    ],
    "Branch_graphrename_734": [
        [
            "COND",
            "Eq_graphrename_735"
        ],
        [
            "FALSE",
            "Branch_graphrename_737"
        ]
    ],
    "'d7_graphrename_685": [],
    "'d1_graphrename_686": [],
    "top.iRECEIVER.rec_dataH_graphrename_687": [
        [
            "",
            "top_iRECEIVER_par_dataH"
        ]
    ],
    "top.iRECEIVER.rec_datH_graphrename_688": [
        [
            "",
            "Branch_graphrename_689"
        ]
    ],
    "Branch_graphrename_689": [
        [
            "COND",
            "Unot_graphrename_690"
        ],
        [
            "TRUE",
            "'d1_graphrename_691"
        ],
        [
            "FALSE",
            "top_iRECEIVER_rec_datSyncH"
        ]
    ],
    "Unot_graphrename_690": [
        [
            "",
            "top_iRECEIVER_sys_rst_l"
        ]
    ],
    "'d1_graphrename_691": [],
    "top_iRECEIVER_rec_datSyncH": [],
    "top.iRECEIVER.rec_datSyncH_graphrename_692": [
        [
            "",
            "Branch_graphrename_693"
        ]
    ],
    "Branch_graphrename_693": [
        [
            "COND",
            "Unot_graphrename_694"
        ],
        [
            "TRUE",
            "'d1_graphrename_695"
        ],
        [
            "FALSE",
            "top_iRECEIVER_uart_dataH"
        ]
    ],
    "Unot_graphrename_694": [
        [
            "",
            "top_iRECEIVER_sys_rst_l"
        ]
    ],
    "'d1_graphrename_695": [],
    "top_iRECEIVER_uart_dataH": [],
    "top.iRECEIVER.rec_readyH_graphrename_696": [
        [
            "",
            "Branch_graphrename_697"
        ]
    ],
    "Branch_graphrename_697": [
        [
            "COND",
            "Unot_graphrename_698"
        ],
        [
            "TRUE",
            "'d0_graphrename_699"
        ],
        [
            "FALSE",
            "top_iRECEIVER_rec_readyInH"
        ]
    ],
    "Unot_graphrename_698": [
        [
            "",
            "top_iRECEIVER_sys_rst_l"
        ]
    ],
    "'d0_graphrename_699": [],
    "top_iRECEIVER_rec_readyInH": [],
    "top.iRECEIVER.rec_readyInH_graphrename_700": [
        [
            "",
            "Branch_graphrename_701"
        ]
    ],
    "Branch_graphrename_701": [
        [
            "COND",
            "Eq_graphrename_702"
        ],
        [
            "TRUE",
            "Branch_graphrename_704"
        ],
        [
            "FALSE",
            "Branch_graphrename_706"
        ]
    ],
    "Eq_graphrename_702": [
        [
            "",
            "top.iRECEIVER.state_graphrename_749"
        ],
        [
            "",
            "3'd1_graphrename_703"
        ]
    ],
    "Branch_graphrename_704": [
        [
            "COND",
            "Unot_graphrename_705"
        ],
        [
            "TRUE",
            "top_iRECEIVER__rn48_rec_readyInH"
        ],
        [
            "FALSE",
            "top_iRECEIVER__rn51_rec_readyInH"
        ]
    ],
    "Branch_graphrename_706": [
        [
            "TRUE",
            "top_iRECEIVER_rec_readyInH"
        ],
        [
            "COND",
            "Eq_graphrename_707"
        ],
        [
            "FALSE",
            "Branch_graphrename_709"
        ]
    ],
    "3'd1_graphrename_703": [],
    "Unot_graphrename_705": [
        [
            "",
            "top_iRECEIVER_rec_datH"
        ]
    ],
    "top_iRECEIVER__rn48_rec_readyInH": [],
    "top_iRECEIVER__rn51_rec_readyInH": [],
    "Eq_graphrename_707": [
        [
            "",
            "top.iRECEIVER.state_graphrename_749"
        ],
        [
            "",
            "3'd2_graphrename_708"
        ]
    ],
    "Branch_graphrename_709": [
        [
            "FALSE",
            "top_iRECEIVER_rec_readyInH"
        ],
        [
            "COND",
            "Eq_graphrename_710"
        ],
        [
            "TRUE",
            "Branch_graphrename_712"
        ]
    ],
    "3'd2_graphrename_708": [],
    "Eq_graphrename_710": [
        [
            "",
            "top.iRECEIVER.state_graphrename_749"
        ],
        [
            "",
            "3'd3_graphrename_711"
        ]
    ],
    "Branch_graphrename_712": [
        [
            "FALSE",
            "top_iRECEIVER_rec_readyInH"
        ],
        [
            "COND",
            "Eq_graphrename_713"
        ],
        [
            "TRUE",
            "Branch_graphrename_715"
        ]
    ],
    "3'd3_graphrename_711": [],
    "Eq_graphrename_713": [
        [
            "",
            "top_iRECEIVER_bitCell_cntrH"
        ],
        [
            "",
            "4'd14_graphrename_714"
        ]
    ],
    "Branch_graphrename_715": [
        [
            "FALSE",
            "top_iRECEIVER_rec_readyInH"
        ],
        [
            "COND",
            "Eq_graphrename_716"
        ],
        [
            "TRUE",
            "top_iRECEIVER__rn56_rec_readyInH"
        ]
    ],
    "4'd14_graphrename_714": [],
    "Eq_graphrename_716": [
        [
            "",
            "top_iRECEIVER_recd_bitCntrH"
        ],
        [
            "",
            "'d8_graphrename_717"
        ]
    ],
    "top_iRECEIVER__rn56_rec_readyInH": [],
    "'d8_graphrename_717": [],
    "top.iRECEIVER.recd_bitCntrH_graphrename_718": [
        [
            "",
            "Branch_graphrename_719"
        ]
    ],
    "Branch_graphrename_719": [
        [
            "COND",
            "Unot_graphrename_720"
        ],
        [
            "TRUE",
            "'d0_graphrename_721"
        ],
        [
            "FALSE",
            "Branch_graphrename_722"
        ]
    ],
    "Unot_graphrename_720": [
        [
            "",
            "top_iRECEIVER_sys_rst_l"
        ]
    ],
    "'d0_graphrename_721": [],
    "Branch_graphrename_722": [
        [
            "",
            "top.iRECEIVER.countH_graphrename_639"
        ],
        [
            "TRUE",
            "Plus_graphrename_723"
        ],
        [
            "FALSE",
            "Branch_graphrename_725"
        ]
    ],
    "Plus_graphrename_723": [
        [
            "",
            "top_iRECEIVER_recd_bitCntrH"
        ],
        [
            "",
            "'d1_graphrename_724"
        ]
    ],
    "Branch_graphrename_725": [
        [
            "FALSE",
            "top_iRECEIVER_recd_bitCntrH"
        ],
        [
            "TRUE",
            "'d0_graphrename_726"
        ],
        [
            "",
            "top.iRECEIVER.rstCountH_graphrename_727"
        ]
    ],
    "'d1_graphrename_724": [],
    "'d0_graphrename_726": [],
    "top.iRECEIVER.rstCountH_graphrename_727": [
        [
            "",
            "Branch_graphrename_728"
        ]
    ],
    "Branch_graphrename_728": [
        [
            "COND",
            "Eq_graphrename_729"
        ],
        [
            "TRUE",
            "Branch_graphrename_731"
        ]
    ],
    "Eq_graphrename_729": [
        [
            "",
            "top.iRECEIVER.state_graphrename_749"
        ],
        [
            "",
            "3'd1_graphrename_730"
        ]
    ],
    "Branch_graphrename_731": [
        [
            "COND",
            "Unot_graphrename_732"
        ],
        [
            "TRUE",
            "top_iRECEIVER__rn47_rstCountH"
        ],
        [
            "FALSE",
            "top_iRECEIVER__rn50_rstCountH"
        ]
    ],
    "3'd1_graphrename_730": [],
    "Unot_graphrename_732": [
        [
            "",
            "top_iRECEIVER_rec_datH"
        ]
    ],
    "top_iRECEIVER__rn47_rstCountH": [],
    "top_iRECEIVER__rn50_rstCountH": [],
    "Eq_graphrename_735": [
        [
            "",
            "top.iRECEIVER.state_graphrename_749"
        ],
        [
            "",
            "3'd1_graphrename_736"
        ]
    ],
    "Branch_graphrename_737": [
        [
            "COND",
            "Eq_graphrename_738"
        ],
        [
            "FALSE",
            "Branch_graphrename_740"
        ]
    ],
    "3'd1_graphrename_736": [],
    "Eq_graphrename_738": [
        [
            "",
            "top.iRECEIVER.state_graphrename_749"
        ],
        [
            "",
            "3'd2_graphrename_739"
        ]
    ],
    "Branch_graphrename_740": [
        [
            "COND",
            "Eq_graphrename_741"
        ],
        [
            "TRUE",
            "Branch_graphrename_743"
        ]
    ],
    "3'd2_graphrename_739": [],
    "Eq_graphrename_741": [
        [
            "",
            "top.iRECEIVER.state_graphrename_749"
        ],
        [
            "",
            "3'd3_graphrename_742"
        ]
    ],
    "Branch_graphrename_743": [
        [
            "COND",
            "Eq_graphrename_744"
        ],
        [
            "TRUE",
            "Branch_graphrename_746"
        ]
    ],
    "3'd3_graphrename_742": [],
    "Eq_graphrename_744": [
        [
            "",
            "top_iRECEIVER_bitCell_cntrH"
        ],
        [
            "",
            "4'd14_graphrename_745"
        ]
    ],
    "Branch_graphrename_746": [
        [
            "COND",
            "Eq_graphrename_747"
        ],
        [
            "TRUE",
            "top_iRECEIVER__rn45_shiftH"
        ],
        [
            "FALSE",
            "top_iRECEIVER__rn57_shiftH"
        ]
    ],
    "4'd14_graphrename_745": [],
    "Eq_graphrename_747": [
        [
            "",
            "top_iRECEIVER_recd_bitCntrH"
        ],
        [
            "",
            "'d8_graphrename_748"
        ]
    ],
    "top_iRECEIVER__rn45_shiftH": [],
    "top_iRECEIVER__rn57_shiftH": [],
    "'d8_graphrename_748": [],
    "Unot_graphrename_751": [
        [
            "",
            "top_iRECEIVER_sys_rst_l"
        ]
    ],
    "3'd1_graphrename_752": [],
    "top.iRECEIVER.sys_clk_graphrename_753": [
        [
            "",
            "top_sys_clk"
        ]
    ],
    "top_sys_clk": [],
    "top.iRECEIVER.sys_rst_l_graphrename_754": [
        [
            "",
            "top_sys_rst_l"
        ]
    ],
    "top_sys_rst_l": [],
    "top.iRECEIVER.uart_dataH_graphrename_755": [
        [
            "",
            "top_uart_REC_dataH"
        ]
    ],
    "top_uart_REC_dataH": [],
    "top.iRECEIVER.WORD_LEN_graphrename_756": [
        [
            "",
            "'d8_graphrename_757"
        ]
    ],
    "'d8_graphrename_757": [],
    "top.iXMIT._rn0_uart_xmitH_graphrename_758": [
        [
            "",
            "1'd0_graphrename_759"
        ]
    ],
    "1'd0_graphrename_759": [],
    "top.iXMIT._rn10_xmitDataSelH_graphrename_760": [
        [
            "",
            "2'd1_graphrename_761"
        ]
    ],
    "2'd1_graphrename_761": [],
    "top.iXMIT._rn11_xmit_doneInH_graphrename_762": [
        [
            "",
            "1'd0_graphrename_763"
        ]
    ],
    "1'd0_graphrename_763": [],
    "top.iXMIT._rn12_next_state_graphrename_764": [
        [
            "",
            "3'd2_graphrename_765"
        ]
    ],
    "3'd2_graphrename_765": [],
    "top.iXMIT._rn13_load_shiftRegH_graphrename_766": [
        [
            "",
            "1'd1_graphrename_767"
        ]
    ],
    "1'd1_graphrename_767": [],
    "top.iXMIT._rn14_next_state_graphrename_768": [
        [
            "",
            "3'd0_graphrename_769"
        ]
    ],
    "3'd0_graphrename_769": [],
    "top.iXMIT._rn15_rst_bitCountH_graphrename_770": [
        [
            "",
            "1'd1_graphrename_771"
        ]
    ],
    "1'd1_graphrename_771": [],
    "top.iXMIT._rn16_xmit_doneInH_graphrename_772": [
        [
            "",
            "1'd1_graphrename_773"
        ]
    ],
    "1'd1_graphrename_773": [],
    "top.iXMIT._rn17_xmitDataSelH_graphrename_774": [
        [
            "",
            "2'd0_graphrename_775"
        ]
    ],
    "2'd0_graphrename_775": [],
    "top.iXMIT._rn18_next_state_graphrename_776": [
        [
            "",
            "3'd3_graphrename_777"
        ]
    ],
    "3'd3_graphrename_777": [],
    "top.iXMIT._rn19_next_state_graphrename_778": [
        [
            "",
            "3'd2_graphrename_779"
        ]
    ],
    "3'd2_graphrename_779": [],
    "top.iXMIT._rn1_uart_xmitH_graphrename_780": [
        [
            "",
            "1'd1_graphrename_781"
        ]
    ],
    "1'd1_graphrename_781": [],
    "top.iXMIT._rn20_countEnaH_graphrename_782": [
        [
            "",
            "1'd1_graphrename_783"
        ]
    ],
    "1'd1_graphrename_783": [],
    "top.iXMIT._rn21_xmitDataSelH_graphrename_784": [
        [
            "",
            "2'd2_graphrename_785"
        ]
    ],
    "2'd2_graphrename_785": [],
    "top.iXMIT._rn22_next_state_graphrename_786": [
        [
            "",
            "3'd5_graphrename_787"
        ]
    ],
    "3'd5_graphrename_787": [],
    "top.iXMIT._rn23_next_state_graphrename_788": [
        [
            "",
            "3'd4_graphrename_789"
        ]
    ],
    "3'd4_graphrename_789": [],
    "top.iXMIT._rn24_ena_bitCountH_graphrename_790": [
        [
            "",
            "1'd1_graphrename_791"
        ]
    ],
    "1'd1_graphrename_791": [],
    "top.iXMIT._rn25_next_state_graphrename_792": [
        [
            "",
            "3'd3_graphrename_793"
        ]
    ],
    "3'd3_graphrename_793": [],
    "top.iXMIT._rn26_countEnaH_graphrename_794": [
        [
            "",
            "1'd1_graphrename_795"
        ]
    ],
    "1'd1_graphrename_795": [],
    "top.iXMIT._rn27_xmitDataSelH_graphrename_796": [
        [
            "",
            "2'd2_graphrename_797"
        ]
    ],
    "2'd2_graphrename_797": [],
    "top.iXMIT._rn28_next_state_graphrename_798": [
        [
            "",
            "3'd3_graphrename_799"
        ]
    ],
    "3'd3_graphrename_799": [],
    "top.iXMIT._rn29_shiftEnaH_graphrename_800": [
        [
            "",
            "1'd1_graphrename_801"
        ]
    ],
    "1'd1_graphrename_801": [],
    "top.iXMIT._rn2_uart_xmitH_graphrename_802": [
        [
            "",
            "PartSelect_graphrename_803"
        ]
    ],
    "PartSelect_graphrename_803": [
        [
            "VAR",
            "top_iXMIT_xmit_ShiftRegH"
        ],
        [
            "MSB",
            "'d0_graphrename_804"
        ],
        [
            "LSB",
            "'d0_graphrename_805"
        ]
    ],
    "top_iXMIT_xmit_ShiftRegH": [],
    "'d0_graphrename_804": [],
    "'d0_graphrename_805": [],
    "top.iXMIT._rn30_xmitDataSelH_graphrename_806": [
        [
            "",
            "2'd1_graphrename_807"
        ]
    ],
    "2'd1_graphrename_807": [],
    "top.iXMIT._rn31_next_state_graphrename_808": [
        [
            "",
            "3'd0_graphrename_809"
        ]
    ],
    "3'd0_graphrename_809": [],
    "top.iXMIT._rn32_xmit_doneInH_graphrename_810": [
        [
            "",
            "1'd1_graphrename_811"
        ]
    ],
    "1'd1_graphrename_811": [],
    "top.iXMIT._rn33_next_state_graphrename_812": [
        [
            "",
            "3'd5_graphrename_813"
        ]
    ],
    "3'd5_graphrename_813": [],
    "top.iXMIT._rn34_countEnaH_graphrename_814": [
        [
            "",
            "1'd1_graphrename_815"
        ]
    ],
    "1'd1_graphrename_815": [],
    "top.iXMIT._rn35_next_state_graphrename_816": [
        [
            "",
            "top_iXMIT__rn35_next_state"
        ]
    ],
    "top_iXMIT__rn35_next_state": [],
    "top.iXMIT._rn36_load_shiftRegH_graphrename_817": [
        [
            "",
            "top_iXMIT__rn36_load_shiftRegH"
        ]
    ],
    "top_iXMIT__rn36_load_shiftRegH": [],
    "top.iXMIT._rn37_countEnaH_graphrename_818": [
        [
            "",
            "top_iXMIT__rn37_countEnaH"
        ]
    ],
    "top_iXMIT__rn37_countEnaH": [],
    "top.iXMIT._rn38_shiftEnaH_graphrename_819": [
        [
            "",
            "top_iXMIT__rn38_shiftEnaH"
        ]
    ],
    "top_iXMIT__rn38_shiftEnaH": [],
    "top.iXMIT._rn39_rst_bitCountH_graphrename_820": [
        [
            "",
            "top_iXMIT__rn39_rst_bitCountH"
        ]
    ],
    "top_iXMIT__rn39_rst_bitCountH": [],
    "top.iXMIT._rn3_uart_xmitH_graphrename_821": [
        [
            "",
            "top_iXMIT__rn3_uart_xmitH"
        ]
    ],
    "top_iXMIT__rn3_uart_xmitH": [],
    "top.iXMIT._rn40_ena_bitCountH_graphrename_822": [
        [
            "",
            "top_iXMIT__rn40_ena_bitCountH"
        ]
    ],
    "top_iXMIT__rn40_ena_bitCountH": [],
    "top.iXMIT._rn41_xmitDataSelH_graphrename_823": [
        [
            "",
            "top_iXMIT__rn41_xmitDataSelH"
        ]
    ],
    "top_iXMIT__rn41_xmitDataSelH": [],
    "top.iXMIT._rn42_xmit_doneInH_graphrename_824": [
        [
            "",
            "top_iXMIT__rn42_xmit_doneInH"
        ]
    ],
    "top_iXMIT__rn42_xmit_doneInH": [],
    "top.iXMIT._rn4_next_state_graphrename_825": [
        [
            "",
            "top.iXMIT.state_graphrename_989"
        ]
    ],
    "top.iXMIT.state_graphrename_989": [
        [
            "",
            "Branch_graphrename_990"
        ]
    ],
    "Branch_graphrename_990": [
        [
            "COND",
            "Unot_graphrename_991"
        ],
        [
            "TRUE",
            "3'd0_graphrename_992"
        ],
        [
            "FALSE",
            "top_iXMIT_next_state"
        ]
    ],
    "top.iXMIT._rn5_load_shiftRegH_graphrename_826": [
        [
            "",
            "1'd0_graphrename_827"
        ]
    ],
    "1'd0_graphrename_827": [],
    "top.iXMIT._rn6_countEnaH_graphrename_828": [
        [
            "",
            "1'd0_graphrename_829"
        ]
    ],
    "1'd0_graphrename_829": [],
    "top.iXMIT._rn7_shiftEnaH_graphrename_830": [
        [
            "",
            "1'd0_graphrename_831"
        ]
    ],
    "1'd0_graphrename_831": [],
    "top.iXMIT._rn8_rst_bitCountH_graphrename_832": [
        [
            "",
            "1'd0_graphrename_833"
        ]
    ],
    "1'd0_graphrename_833": [],
    "top.iXMIT._rn9_ena_bitCountH_graphrename_834": [
        [
            "",
            "1'd0_graphrename_835"
        ]
    ],
    "1'd0_graphrename_835": [],
    "top.iXMIT.bitCell_cntrH_graphrename_836": [
        [
            "",
            "Branch_graphrename_837"
        ]
    ],
    "Branch_graphrename_837": [
        [
            "COND",
            "Eq_graphrename_838"
        ],
        [
            "TRUE",
            "Branch_graphrename_840"
        ],
        [
            "FALSE",
            "top_iXMIT_bitCell_cntrH"
        ]
    ],
    "Eq_graphrename_838": [
        [
            "",
            "top.iXMIT.state_graphrename_989"
        ],
        [
            "",
            "3'd0_graphrename_839"
        ]
    ],
    "Branch_graphrename_840": [
        [
            "TRUE",
            "'d0_graphrename_841"
        ],
        [
            "FALSE",
            "Branch_graphrename_842"
        ],
        [
            "",
            "top.iXMIT.xmitH_graphrename_1146"
        ]
    ],
    "top_iXMIT_bitCell_cntrH": [],
    "3'd0_graphrename_839": [],
    "'d0_graphrename_841": [],
    "Branch_graphrename_842": [
        [
            "COND",
            "Unot_graphrename_843"
        ],
        [
            "TRUE",
            "'d0_graphrename_844"
        ],
        [
            "FALSE",
            "Branch_graphrename_845"
        ]
    ],
    "top.iXMIT.xmitH_graphrename_1146": [
        [
            "",
            "top_xmitH"
        ]
    ],
    "Unot_graphrename_843": [
        [
            "",
            "top_iXMIT_sys_rst_l"
        ]
    ],
    "'d0_graphrename_844": [],
    "Branch_graphrename_845": [
        [
            "TRUE",
            "Plus_graphrename_846"
        ],
        [
            "FALSE",
            "'d0_graphrename_848"
        ],
        [
            "",
            "top.iXMIT.countEnaH_graphrename_863"
        ]
    ],
    "top_xmitH": [],
    "top_iXMIT_sys_rst_l": [],
    "Plus_graphrename_846": [
        [
            "",
            "top_iXMIT_bitCell_cntrH"
        ],
        [
            "",
            "'d1_graphrename_847"
        ]
    ],
    "'d0_graphrename_848": [],
    "top.iXMIT.countEnaH_graphrename_863": [
        [
            "",
            "Branch_graphrename_864"
        ]
    ],
    "'d1_graphrename_847": [],
    "Branch_graphrename_864": [
        [
            "COND",
            "Eq_graphrename_865"
        ],
        [
            "FALSE",
            "Branch_graphrename_867"
        ]
    ],
    "top.iXMIT.bitCountH_graphrename_849": [
        [
            "",
            "Branch_graphrename_850"
        ]
    ],
    "Branch_graphrename_850": [
        [
            "COND",
            "Eq_graphrename_851"
        ],
        [
            "TRUE",
            "Branch_graphrename_853"
        ]
    ],
    "Eq_graphrename_851": [
        [
            "",
            "top.iXMIT.state_graphrename_989"
        ],
        [
            "",
            "3'd0_graphrename_852"
        ]
    ],
    "Branch_graphrename_853": [
        [
            "",
            "top.iXMIT.xmitH_graphrename_1146"
        ],
        [
            "TRUE",
            "'d0_graphrename_854"
        ],
        [
            "FALSE",
            "Branch_graphrename_855"
        ]
    ],
    "3'd0_graphrename_852": [],
    "'d0_graphrename_854": [],
    "Branch_graphrename_855": [
        [
            "COND",
            "Unot_graphrename_856"
        ],
        [
            "TRUE",
            "'d0_graphrename_857"
        ],
        [
            "FALSE",
            "Branch_graphrename_858"
        ]
    ],
    "Unot_graphrename_856": [
        [
            "",
            "top_iXMIT_sys_rst_l"
        ]
    ],
    "'d0_graphrename_857": [],
    "Branch_graphrename_858": [
        [
            "COND",
            "top_iXMIT_rst_bitCountH"
        ],
        [
            "TRUE",
            "'d0_graphrename_859"
        ],
        [
            "FALSE",
            "Branch_graphrename_860"
        ]
    ],
    "top_iXMIT_rst_bitCountH": [],
    "'d0_graphrename_859": [],
    "Branch_graphrename_860": [
        [
            "COND",
            "top_iXMIT_ena_bitCountH"
        ],
        [
            "TRUE",
            "Plus_graphrename_861"
        ]
    ],
    "top_iXMIT_ena_bitCountH": [],
    "Plus_graphrename_861": [
        [
            "",
            "'d1_graphrename_862"
        ]
    ],
    "'d1_graphrename_862": [],
    "Eq_graphrename_865": [
        [
            "",
            "top.iXMIT.state_graphrename_989"
        ],
        [
            "",
            "3'd0_graphrename_866"
        ]
    ],
    "Branch_graphrename_867": [
        [
            "COND",
            "Eq_graphrename_868"
        ],
        [
            "TRUE",
            "Branch_graphrename_870"
        ],
        [
            "FALSE",
            "Branch_graphrename_873"
        ]
    ],
    "3'd0_graphrename_866": [],
    "Eq_graphrename_868": [
        [
            "",
            "top.iXMIT.state_graphrename_989"
        ],
        [
            "",
            "3'd2_graphrename_869"
        ]
    ],
    "Branch_graphrename_870": [
        [
            "COND",
            "Eq_graphrename_871"
        ],
        [
            "TRUE",
            "top_iXMIT__rn6_countEnaH"
        ],
        [
            "FALSE",
            "top_iXMIT__rn20_countEnaH"
        ]
    ],
    "Branch_graphrename_873": [
        [
            "COND",
            "Eq_graphrename_874"
        ],
        [
            "TRUE",
            "Branch_graphrename_876"
        ],
        [
            "FALSE",
            "Branch_graphrename_879"
        ]
    ],
    "3'd2_graphrename_869": [],
    "Eq_graphrename_871": [
        [
            "",
            "top_iXMIT_bitCell_cntrH"
        ],
        [
            "",
            "4'd15_graphrename_872"
        ]
    ],
    "top_iXMIT__rn6_countEnaH": [],
    "top_iXMIT__rn20_countEnaH": [],
    "Eq_graphrename_874": [
        [
            "",
            "top.iXMIT.state_graphrename_989"
        ],
        [
            "",
            "3'd3_graphrename_875"
        ]
    ],
    "Branch_graphrename_876": [
        [
            "COND",
            "Eq_graphrename_877"
        ],
        [
            "FALSE",
            "top_iXMIT__rn26_countEnaH"
        ]
    ],
    "Branch_graphrename_879": [
        [
            "COND",
            "Eq_graphrename_880"
        ],
        [
            "FALSE",
            "Branch_graphrename_882"
        ]
    ],
    "4'd15_graphrename_872": [],
    "3'd3_graphrename_875": [],
    "Eq_graphrename_877": [
        [
            "",
            "top_iXMIT_bitCell_cntrH"
        ],
        [
            "",
            "4'd14_graphrename_878"
        ]
    ],
    "top_iXMIT__rn26_countEnaH": [],
    "Eq_graphrename_880": [
        [
            "",
            "top.iXMIT.state_graphrename_989"
        ],
        [
            "",
            "3'd4_graphrename_881"
        ]
    ],
    "Branch_graphrename_882": [
        [
            "FALSE",
            "top_iXMIT__rn37_countEnaH"
        ],
        [
            "COND",
            "Eq_graphrename_883"
        ],
        [
            "TRUE",
            "Branch_graphrename_885"
        ]
    ],
    "4'd14_graphrename_878": [],
    "3'd4_graphrename_881": [],
    "Eq_graphrename_883": [
        [
            "",
            "top.iXMIT.state_graphrename_989"
        ],
        [
            "",
            "3'd5_graphrename_884"
        ]
    ],
    "Branch_graphrename_885": [
        [
            "COND",
            "Eq_graphrename_886"
        ],
        [
            "FALSE",
            "top_iXMIT__rn34_countEnaH"
        ]
    ],
    "3'd5_graphrename_884": [],
    "Eq_graphrename_886": [
        [
            "",
            "top_iXMIT_bitCell_cntrH"
        ],
        [
            "",
            "4'd15_graphrename_887"
        ]
    ],
    "top_iXMIT__rn34_countEnaH": [],
    "4'd15_graphrename_887": [],
    "top.iXMIT.ena_bitCountH_graphrename_888": [
        [
            "",
            "Branch_graphrename_889"
        ]
    ],
    "Branch_graphrename_889": [
        [
            "TRUE",
            "top_iXMIT_ena_bitCountH"
        ],
        [
            "COND",
            "Eq_graphrename_890"
        ],
        [
            "FALSE",
            "Branch_graphrename_892"
        ]
    ],
    "Eq_graphrename_890": [
        [
            "",
            "top.iXMIT.state_graphrename_989"
        ],
        [
            "",
            "3'd0_graphrename_891"
        ]
    ],
    "Branch_graphrename_892": [
        [
            "TRUE",
            "top_iXMIT_ena_bitCountH"
        ],
        [
            "COND",
            "Eq_graphrename_893"
        ],
        [
            "FALSE",
            "Branch_graphrename_895"
        ]
    ],
    "3'd0_graphrename_891": [],
    "Eq_graphrename_893": [
        [
            "",
            "top.iXMIT.state_graphrename_989"
        ],
        [
            "",
            "3'd2_graphrename_894"
        ]
    ],
    "Branch_graphrename_895": [
        [
            "COND",
            "Eq_graphrename_896"
        ],
        [
            "TRUE",
            "Branch_graphrename_898"
        ],
        [
            "FALSE",
            "Branch_graphrename_904"
        ]
    ],
    "3'd2_graphrename_894": [],
    "Eq_graphrename_896": [
        [
            "",
            "top.iXMIT.state_graphrename_989"
        ],
        [
            "",
            "3'd3_graphrename_897"
        ]
    ],
    "Branch_graphrename_898": [
        [
            "FALSE",
            "top_iXMIT_ena_bitCountH"
        ],
        [
            "COND",
            "Eq_graphrename_899"
        ],
        [
            "TRUE",
            "Branch_graphrename_901"
        ]
    ],
    "Branch_graphrename_904": [
        [
            "TRUE",
            "top_iXMIT_ena_bitCountH"
        ],
        [
            "COND",
            "Eq_graphrename_905"
        ],
        [
            "FALSE",
            "Branch_graphrename_907"
        ]
    ],
    "3'd3_graphrename_897": [],
    "Eq_graphrename_899": [
        [
            "",
            "top_iXMIT_bitCell_cntrH"
        ],
        [
            "",
            "4'd14_graphrename_900"
        ]
    ],
    "Branch_graphrename_901": [
        [
            "COND",
            "Eq_graphrename_902"
        ],
        [
            "TRUE",
            "top_iXMIT__rn9_ena_bitCountH"
        ],
        [
            "FALSE",
            "top_iXMIT__rn24_ena_bitCountH"
        ]
    ],
    "Eq_graphrename_905": [
        [
            "",
            "top.iXMIT.state_graphrename_989"
        ],
        [
            "",
            "3'd4_graphrename_906"
        ]
    ],
    "Branch_graphrename_907": [
        [
            "FALSE",
            "top_iXMIT__rn40_ena_bitCountH"
        ],
        [
            "TRUE",
            "top_iXMIT_ena_bitCountH"
        ],
        [
            "COND",
            "Eq_graphrename_908"
        ]
    ],
    "4'd14_graphrename_900": [],
    "Eq_graphrename_902": [
        [
            "",
            "top.iXMIT.bitCountH_graphrename_849"
        ],
        [
            "",
            "'d8_graphrename_903"
        ]
    ],
    "top_iXMIT__rn9_ena_bitCountH": [],
    "top_iXMIT__rn24_ena_bitCountH": [],
    "'d8_graphrename_903": [],
    "3'd4_graphrename_906": [],
    "Eq_graphrename_908": [
        [
            "",
            "top.iXMIT.state_graphrename_989"
        ],
        [
            "",
            "3'd5_graphrename_909"
        ]
    ],
    "3'd5_graphrename_909": [],
    "top.iXMIT.load_shiftRegH_graphrename_910": [
        [
            "",
            "Branch_graphrename_911"
        ]
    ],
    "Branch_graphrename_911": [
        [
            "COND",
            "Eq_graphrename_912"
        ],
        [
            "TRUE",
            "Branch_graphrename_914"
        ],
        [
            "FALSE",
            "Branch_graphrename_915"
        ]
    ],
    "Eq_graphrename_912": [
        [
            "",
            "top.iXMIT.state_graphrename_989"
        ],
        [
            "",
            "3'd0_graphrename_913"
        ]
    ],
    "Branch_graphrename_914": [
        [
            "",
            "top.iXMIT.xmitH_graphrename_1146"
        ],
        [
            "TRUE",
            "top_iXMIT__rn13_load_shiftRegH"
        ],
        [
            "FALSE",
            "top_iXMIT__rn5_load_shiftRegH"
        ]
    ],
    "Branch_graphrename_915": [
        [
            "COND",
            "Eq_graphrename_916"
        ],
        [
            "TRUE",
            "top_iXMIT_load_shiftRegH"
        ],
        [
            "FALSE",
            "Branch_graphrename_918"
        ]
    ],
    "3'd0_graphrename_913": [],
    "top_iXMIT__rn13_load_shiftRegH": [],
    "top_iXMIT__rn5_load_shiftRegH": [],
    "Eq_graphrename_916": [
        [
            "",
            "top.iXMIT.state_graphrename_989"
        ],
        [
            "",
            "3'd2_graphrename_917"
        ]
    ],
    "top_iXMIT_load_shiftRegH": [],
    "Branch_graphrename_918": [
        [
            "TRUE",
            "top_iXMIT_load_shiftRegH"
        ],
        [
            "COND",
            "Eq_graphrename_919"
        ],
        [
            "FALSE",
            "Branch_graphrename_921"
        ]
    ],
    "3'd2_graphrename_917": [],
    "Eq_graphrename_919": [
        [
            "",
            "top.iXMIT.state_graphrename_989"
        ],
        [
            "",
            "3'd3_graphrename_920"
        ]
    ],
    "Branch_graphrename_921": [
        [
            "TRUE",
            "top_iXMIT_load_shiftRegH"
        ],
        [
            "COND",
            "Eq_graphrename_922"
        ],
        [
            "FALSE",
            "Branch_graphrename_924"
        ]
    ],
    "3'd3_graphrename_920": [],
    "Eq_graphrename_922": [
        [
            "",
            "top.iXMIT.state_graphrename_989"
        ],
        [
            "",
            "3'd4_graphrename_923"
        ]
    ],
    "Branch_graphrename_924": [
        [
            "FALSE",
            "top_iXMIT__rn36_load_shiftRegH"
        ],
        [
            "TRUE",
            "top_iXMIT_load_shiftRegH"
        ],
        [
            "COND",
            "Eq_graphrename_925"
        ]
    ],
    "3'd4_graphrename_923": [],
    "Eq_graphrename_925": [
        [
            "",
            "top.iXMIT.state_graphrename_989"
        ],
        [
            "",
            "3'd5_graphrename_926"
        ]
    ],
    "3'd5_graphrename_926": [],
    "top.iXMIT.next_state_graphrename_927": [
        [
            "",
            "Branch_graphrename_928"
        ]
    ],
    "Branch_graphrename_928": [
        [
            "COND",
            "Eq_graphrename_929"
        ],
        [
            "TRUE",
            "Branch_graphrename_931"
        ],
        [
            "FALSE",
            "Branch_graphrename_932"
        ]
    ],
    "Eq_graphrename_929": [
        [
            "",
            "top.iXMIT.state_graphrename_989"
        ],
        [
            "",
            "3'd0_graphrename_930"
        ]
    ],
    "Branch_graphrename_931": [
        [
            "",
            "top.iXMIT.xmitH_graphrename_1146"
        ],
        [
            "TRUE",
            "top_iXMIT__rn12_next_state"
        ],
        [
            "FALSE",
            "top_iXMIT__rn14_next_state"
        ]
    ],
    "Branch_graphrename_932": [
        [
            "COND",
            "Eq_graphrename_933"
        ],
        [
            "TRUE",
            "Branch_graphrename_935"
        ],
        [
            "FALSE",
            "Branch_graphrename_938"
        ]
    ],
    "3'd0_graphrename_930": [],
    "top_iXMIT__rn12_next_state": [],
    "top_iXMIT__rn14_next_state": [],
    "Eq_graphrename_933": [
        [
            "",
            "top.iXMIT.state_graphrename_989"
        ],
        [
            "",
            "3'd2_graphrename_934"
        ]
    ],
    "Branch_graphrename_935": [
        [
            "COND",
            "Eq_graphrename_936"
        ],
        [
            "TRUE",
            "top_iXMIT__rn18_next_state"
        ],
        [
            "FALSE",
            "top_iXMIT__rn19_next_state"
        ]
    ],
    "Branch_graphrename_938": [
        [
            "COND",
            "Eq_graphrename_939"
        ],
        [
            "TRUE",
            "Branch_graphrename_941"
        ],
        [
            "FALSE",
            "Branch_graphrename_947"
        ]
    ],
    "3'd2_graphrename_934": [],
    "Eq_graphrename_936": [
        [
            "",
            "top_iXMIT_bitCell_cntrH"
        ],
        [
            "",
            "4'd15_graphrename_937"
        ]
    ],
    "top_iXMIT__rn18_next_state": [],
    "top_iXMIT__rn19_next_state": [],
    "Eq_graphrename_939": [
        [
            "",
            "top.iXMIT.state_graphrename_989"
        ],
        [
            "",
            "3'd3_graphrename_940"
        ]
    ],
    "Branch_graphrename_941": [
        [
            "COND",
            "Eq_graphrename_942"
        ],
        [
            "TRUE",
            "Branch_graphrename_944"
        ],
        [
            "FALSE",
            "top_iXMIT__rn25_next_state"
        ]
    ],
    "Branch_graphrename_947": [
        [
            "COND",
            "Eq_graphrename_948"
        ],
        [
            "TRUE",
            "top_iXMIT__rn28_next_state"
        ],
        [
            "FALSE",
            "Branch_graphrename_950"
        ]
    ],
    "4'd15_graphrename_937": [],
    "3'd3_graphrename_940": [],
    "Eq_graphrename_942": [
        [
            "",
            "top_iXMIT_bitCell_cntrH"
        ],
        [
            "",
            "4'd14_graphrename_943"
        ]
    ],
    "Branch_graphrename_944": [
        [
            "COND",
            "Eq_graphrename_945"
        ],
        [
            "TRUE",
            "top_iXMIT__rn22_next_state"
        ],
        [
            "FALSE",
            "top_iXMIT__rn23_next_state"
        ]
    ],
    "top_iXMIT__rn25_next_state": [],
    "Eq_graphrename_948": [
        [
            "",
            "top.iXMIT.state_graphrename_989"
        ],
        [
            "",
            "3'd4_graphrename_949"
        ]
    ],
    "top_iXMIT__rn28_next_state": [],
    "Branch_graphrename_950": [
        [
            "FALSE",
            "top_iXMIT__rn35_next_state"
        ],
        [
            "COND",
            "Eq_graphrename_951"
        ],
        [
            "TRUE",
            "Branch_graphrename_953"
        ]
    ],
    "4'd14_graphrename_943": [],
    "Eq_graphrename_945": [
        [
            "",
            "top.iXMIT.bitCountH_graphrename_849"
        ],
        [
            "",
            "'d8_graphrename_946"
        ]
    ],
    "top_iXMIT__rn22_next_state": [],
    "top_iXMIT__rn23_next_state": [],
    "'d8_graphrename_946": [],
    "3'd4_graphrename_949": [],
    "Eq_graphrename_951": [
        [
            "",
            "top.iXMIT.state_graphrename_989"
        ],
        [
            "",
            "3'd5_graphrename_952"
        ]
    ],
    "Branch_graphrename_953": [
        [
            "COND",
            "Eq_graphrename_954"
        ],
        [
            "TRUE",
            "top_iXMIT__rn31_next_state"
        ],
        [
            "FALSE",
            "top_iXMIT__rn33_next_state"
        ]
    ],
    "3'd5_graphrename_952": [],
    "Eq_graphrename_954": [
        [
            "",
            "top_iXMIT_bitCell_cntrH"
        ],
        [
            "",
            "4'd15_graphrename_955"
        ]
    ],
    "top_iXMIT__rn31_next_state": [],
    "top_iXMIT__rn33_next_state": [],
    "4'd15_graphrename_955": [],
    "top.iXMIT.rst_bitCountH_graphrename_956": [
        [
            "",
            "Branch_graphrename_957"
        ]
    ],
    "Branch_graphrename_957": [
        [
            "COND",
            "Eq_graphrename_958"
        ],
        [
            "TRUE",
            "Branch_graphrename_960"
        ],
        [
            "FALSE",
            "Branch_graphrename_961"
        ]
    ],
    "Eq_graphrename_958": [
        [
            "",
            "top.iXMIT.state_graphrename_989"
        ],
        [
            "",
            "3'd0_graphrename_959"
        ]
    ],
    "Branch_graphrename_960": [
        [
            "",
            "top.iXMIT.xmitH_graphrename_1146"
        ],
        [
            "TRUE",
            "top_iXMIT__rn8_rst_bitCountH"
        ],
        [
            "FALSE",
            "top_iXMIT__rn15_rst_bitCountH"
        ]
    ],
    "Branch_graphrename_961": [
        [
            "TRUE",
            "top_iXMIT_rst_bitCountH"
        ],
        [
            "COND",
            "Eq_graphrename_962"
        ],
        [
            "FALSE",
            "Branch_graphrename_964"
        ]
    ],
    "3'd0_graphrename_959": [],
    "top_iXMIT__rn8_rst_bitCountH": [],
    "top_iXMIT__rn15_rst_bitCountH": [],
    "Eq_graphrename_962": [
        [
            "",
            "top.iXMIT.state_graphrename_989"
        ],
        [
            "",
            "3'd2_graphrename_963"
        ]
    ],
    "Branch_graphrename_964": [
        [
            "TRUE",
            "top_iXMIT_rst_bitCountH"
        ],
        [
            "COND",
            "Eq_graphrename_965"
        ],
        [
            "FALSE",
            "Branch_graphrename_967"
        ]
    ],
    "3'd2_graphrename_963": [],
    "Eq_graphrename_965": [
        [
            "",
            "top.iXMIT.state_graphrename_989"
        ],
        [
            "",
            "3'd3_graphrename_966"
        ]
    ],
    "Branch_graphrename_967": [
        [
            "TRUE",
            "top_iXMIT_rst_bitCountH"
        ],
        [
            "COND",
            "Eq_graphrename_968"
        ],
        [
            "FALSE",
            "Branch_graphrename_970"
        ]
    ],
    "3'd3_graphrename_966": [],
    "Eq_graphrename_968": [
        [
            "",
            "top.iXMIT.state_graphrename_989"
        ],
        [
            "",
            "3'd4_graphrename_969"
        ]
    ],
    "Branch_graphrename_970": [
        [
            "FALSE",
            "top_iXMIT__rn39_rst_bitCountH"
        ],
        [
            "TRUE",
            "top_iXMIT_rst_bitCountH"
        ],
        [
            "COND",
            "Eq_graphrename_971"
        ]
    ],
    "3'd4_graphrename_969": [],
    "Eq_graphrename_971": [
        [
            "",
            "top.iXMIT.state_graphrename_989"
        ],
        [
            "",
            "3'd5_graphrename_972"
        ]
    ],
    "3'd5_graphrename_972": [],
    "top.iXMIT.shiftEnaH_graphrename_973": [
        [
            "",
            "Branch_graphrename_974"
        ]
    ],
    "Branch_graphrename_974": [
        [
            "COND",
            "Eq_graphrename_975"
        ],
        [
            "FALSE",
            "Branch_graphrename_977"
        ]
    ],
    "Eq_graphrename_975": [
        [
            "",
            "top.iXMIT.state_graphrename_989"
        ],
        [
            "",
            "3'd0_graphrename_976"
        ]
    ],
    "Branch_graphrename_977": [
        [
            "COND",
            "Eq_graphrename_978"
        ],
        [
            "FALSE",
            "Branch_graphrename_980"
        ]
    ],
    "3'd0_graphrename_976": [],
    "Eq_graphrename_978": [
        [
            "",
            "top.iXMIT.state_graphrename_989"
        ],
        [
            "",
            "3'd2_graphrename_979"
        ]
    ],
    "Branch_graphrename_980": [
        [
            "COND",
            "Eq_graphrename_981"
        ],
        [
            "FALSE",
            "Branch_graphrename_983"
        ]
    ],
    "3'd2_graphrename_979": [],
    "Eq_graphrename_981": [
        [
            "",
            "top.iXMIT.state_graphrename_989"
        ],
        [
            "",
            "3'd3_graphrename_982"
        ]
    ],
    "Branch_graphrename_983": [
        [
            "COND",
            "Eq_graphrename_984"
        ],
        [
            "TRUE",
            "top_iXMIT__rn29_shiftEnaH"
        ],
        [
            "FALSE",
            "Branch_graphrename_986"
        ]
    ],
    "3'd3_graphrename_982": [],
    "Eq_graphrename_984": [
        [
            "",
            "top.iXMIT.state_graphrename_989"
        ],
        [
            "",
            "3'd4_graphrename_985"
        ]
    ],
    "top_iXMIT__rn29_shiftEnaH": [],
    "Branch_graphrename_986": [
        [
            "FALSE",
            "top_iXMIT__rn38_shiftEnaH"
        ],
        [
            "COND",
            "Eq_graphrename_987"
        ]
    ],
    "3'd4_graphrename_985": [],
    "Eq_graphrename_987": [
        [
            "",
            "top.iXMIT.state_graphrename_989"
        ],
        [
            "",
            "3'd5_graphrename_988"
        ]
    ],
    "3'd5_graphrename_988": [],
    "Unot_graphrename_991": [
        [
            "",
            "top_iXMIT_sys_rst_l"
        ]
    ],
    "3'd0_graphrename_992": [],
    "top_iXMIT_next_state": [],
    "top.iXMIT.sys_clk_graphrename_993": [
        [
            "",
            "top_sys_clk"
        ]
    ],
    "top.iXMIT.sys_rst_l_graphrename_994": [
        [
            "",
            "top_sys_rst_l"
        ]
    ],
    "top.iXMIT.uart_xmitH_graphrename_995": [
        [
            "",
            "Branch_graphrename_996"
        ]
    ],
    "Branch_graphrename_996": [
        [
            "COND",
            "Eq_graphrename_997"
        ],
        [
            "TRUE",
            "top_iXMIT__rn0_uart_xmitH"
        ],
        [
            "FALSE",
            "Branch_graphrename_999"
        ]
    ],
    "Eq_graphrename_997": [
        [
            "",
            "2'd0_graphrename_998"
        ],
        [
            "",
            "top.iXMIT.xmitDataSelH_graphrename_1130"
        ]
    ],
    "top_iXMIT__rn0_uart_xmitH": [],
    "Branch_graphrename_999": [
        [
            "COND",
            "Eq_graphrename_1000"
        ],
        [
            "TRUE",
            "top_iXMIT__rn1_uart_xmitH"
        ],
        [
            "FALSE",
            "Branch_graphrename_1002"
        ]
    ],
    "2'd0_graphrename_998": [],
    "top.iXMIT.xmitDataSelH_graphrename_1130": [
        [
            "",
            "Branch_graphrename_1131"
        ]
    ],
    "Eq_graphrename_1000": [
        [
            "",
            "top.iXMIT.xmitDataSelH_graphrename_1130"
        ],
        [
            "",
            "2'd1_graphrename_1001"
        ]
    ],
    "top_iXMIT__rn1_uart_xmitH": [],
    "Branch_graphrename_1002": [
        [
            "FALSE",
            "top_iXMIT__rn3_uart_xmitH"
        ],
        [
            "COND",
            "Eq_graphrename_1003"
        ],
        [
            "TRUE",
            "top_iXMIT__rn2_uart_xmitH"
        ]
    ],
    "Branch_graphrename_1131": [
        [
            "COND",
            "Eq_graphrename_1132"
        ],
        [
            "FALSE",
            "Branch_graphrename_1134"
        ]
    ],
    "2'd1_graphrename_1001": [],
    "Eq_graphrename_1003": [
        [
            "",
            "top.iXMIT.xmitDataSelH_graphrename_1130"
        ],
        [
            "",
            "2'd2_graphrename_1004"
        ]
    ],
    "top_iXMIT__rn2_uart_xmitH": [],
    "2'd2_graphrename_1004": [],
    "top.iXMIT.WORD_LEN_graphrename_1005": [
        [
            "",
            "'d8_graphrename_1006"
        ]
    ],
    "'d8_graphrename_1006": [],
    "top.iXMIT.xmit_dataH_graphrename_1007": [
        [
            "",
            "top_xmit_dataH"
        ]
    ],
    "top_xmit_dataH": [],
    "top.iXMIT.xmit_doneH_graphrename_1008": [
        [
            "",
            "Branch_graphrename_1009"
        ]
    ],
    "Branch_graphrename_1009": [
        [
            "COND",
            "Unot_graphrename_1010"
        ],
        [
            "TRUE",
            "'d0_graphrename_1011"
        ],
        [
            "FALSE",
            "top_iXMIT_xmit_doneInH"
        ]
    ],
    "Unot_graphrename_1010": [
        [
            "",
            "top_iXMIT_sys_rst_l"
        ]
    ],
    "'d0_graphrename_1011": [],
    "top_iXMIT_xmit_doneInH": [],
    "top.iXMIT.xmit_doneInH_graphrename_1012": [
        [
            "",
            "Branch_graphrename_1013"
        ]
    ],
    "Branch_graphrename_1013": [
        [
            "COND",
            "Eq_graphrename_1014"
        ],
        [
            "TRUE",
            "Branch_graphrename_1016"
        ],
        [
            "FALSE",
            "Branch_graphrename_1017"
        ]
    ],
    "Eq_graphrename_1014": [
        [
            "",
            "top.iXMIT.state_graphrename_989"
        ],
        [
            "",
            "3'd0_graphrename_1015"
        ]
    ],
    "Branch_graphrename_1016": [
        [
            "",
            "top.iXMIT.xmitH_graphrename_1146"
        ],
        [
            "TRUE",
            "top_iXMIT__rn11_xmit_doneInH"
        ],
        [
            "FALSE",
            "top_iXMIT__rn16_xmit_doneInH"
        ]
    ],
    "Branch_graphrename_1017": [
        [
            "TRUE",
            "top_iXMIT_xmit_doneInH"
        ],
        [
            "COND",
            "Eq_graphrename_1018"
        ],
        [
            "FALSE",
            "Branch_graphrename_1020"
        ]
    ],
    "3'd0_graphrename_1015": [],
    "top_iXMIT__rn11_xmit_doneInH": [],
    "top_iXMIT__rn16_xmit_doneInH": [],
    "Eq_graphrename_1018": [
        [
            "",
            "top.iXMIT.state_graphrename_989"
        ],
        [
            "",
            "3'd2_graphrename_1019"
        ]
    ],
    "Branch_graphrename_1020": [
        [
            "TRUE",
            "top_iXMIT_xmit_doneInH"
        ],
        [
            "COND",
            "Eq_graphrename_1021"
        ],
        [
            "FALSE",
            "Branch_graphrename_1023"
        ]
    ],
    "3'd2_graphrename_1019": [],
    "Eq_graphrename_1021": [
        [
            "",
            "top.iXMIT.state_graphrename_989"
        ],
        [
            "",
            "3'd3_graphrename_1022"
        ]
    ],
    "Branch_graphrename_1023": [
        [
            "TRUE",
            "top_iXMIT_xmit_doneInH"
        ],
        [
            "COND",
            "Eq_graphrename_1024"
        ],
        [
            "FALSE",
            "Branch_graphrename_1026"
        ]
    ],
    "3'd3_graphrename_1022": [],
    "Eq_graphrename_1024": [
        [
            "",
            "top.iXMIT.state_graphrename_989"
        ],
        [
            "",
            "3'd4_graphrename_1025"
        ]
    ],
    "Branch_graphrename_1026": [
        [
            "FALSE",
            "top_iXMIT__rn42_xmit_doneInH"
        ],
        [
            "COND",
            "Eq_graphrename_1027"
        ],
        [
            "TRUE",
            "Branch_graphrename_1029"
        ]
    ],
    "3'd4_graphrename_1025": [],
    "Eq_graphrename_1027": [
        [
            "",
            "top.iXMIT.state_graphrename_989"
        ],
        [
            "",
            "3'd5_graphrename_1028"
        ]
    ],
    "Branch_graphrename_1029": [
        [
            "FALSE",
            "top_iXMIT_xmit_doneInH"
        ],
        [
            "COND",
            "Eq_graphrename_1030"
        ],
        [
            "TRUE",
            "top_iXMIT__rn32_xmit_doneInH"
        ]
    ],
    "3'd5_graphrename_1028": [],
    "Eq_graphrename_1030": [
        [
            "",
            "top_iXMIT_bitCell_cntrH"
        ],
        [
            "",
            "4'd15_graphrename_1031"
        ]
    ],
    "top_iXMIT__rn32_xmit_doneInH": [],
    "4'd15_graphrename_1031": [],
    "top.iXMIT.xmit_ShiftRegH_graphrename_1032": [
        [
            "",
            "Branch_graphrename_1033"
        ]
    ],
    "Branch_graphrename_1033": [
        [
            "COND",
            "Unot_graphrename_1034"
        ],
        [
            "TRUE",
            "Branch_graphrename_1035"
        ],
        [
            "FALSE",
            "Branch_graphrename_1062"
        ]
    ],
    "Unot_graphrename_1034": [
        [
            "",
            "top_iXMIT_sys_rst_l"
        ]
    ],
    "Branch_graphrename_1035": [
        [
            "FALSE",
            "top_iXMIT_xmit_ShiftRegH"
        ],
        [
            "COND",
            "Eq_graphrename_1036"
        ],
        [
            "TRUE",
            "Branch_graphrename_1038"
        ]
    ],
    "Branch_graphrename_1062": [
        [
            "COND",
            "top_iXMIT_load_shiftRegH"
        ],
        [
            "TRUE",
            "Branch_graphrename_1063"
        ],
        [
            "FALSE",
            "Branch_graphrename_1093"
        ]
    ],
    "Eq_graphrename_1036": [
        [
            "",
            "top.iXMIT.state_graphrename_989"
        ],
        [
            "",
            "3'd0_graphrename_1037"
        ]
    ],
    "Branch_graphrename_1038": [
        [
            "",
            "top.iXMIT.xmitH_graphrename_1146"
        ],
        [
            "TRUE",
            "8'd0_graphrename_1039"
        ],
        [
            "FALSE",
            "Branch_graphrename_1040"
        ]
    ],
    "Branch_graphrename_1063": [
        [
            "FALSE",
            "top_iXMIT_xmit_ShiftRegH"
        ],
        [
            "COND",
            "Eq_graphrename_1064"
        ],
        [
            "TRUE",
            "Branch_graphrename_1066"
        ]
    ],
    "Branch_graphrename_1093": [
        [
            "",
            "top.iXMIT.shiftEnaH_graphrename_973"
        ],
        [
            "TRUE",
            "Concat_graphrename_1094"
        ],
        [
            "FALSE",
            "Branch_graphrename_1099"
        ]
    ],
    "3'd0_graphrename_1037": [],
    "8'd0_graphrename_1039": [],
    "Branch_graphrename_1040": [
        [
            "COND",
            "Unot_graphrename_1041"
        ],
        [
            "TRUE",
            "Concat_graphrename_1042"
        ],
        [
            "FALSE",
            "Concat_graphrename_1045"
        ]
    ],
    "Unot_graphrename_1041": [
        [
            "",
            "top_iXMIT_sys_rst_l"
        ]
    ],
    "Concat_graphrename_1042": [
        [
            "",
            "1'd0_graphrename_1043"
        ],
        [
            "",
            "7'd0_graphrename_1044"
        ]
    ],
    "Concat_graphrename_1045": [
        [
            "",
            "Branch_graphrename_1046"
        ],
        [
            "",
            "Branch_graphrename_1054"
        ]
    ],
    "1'd0_graphrename_1043": [],
    "7'd0_graphrename_1044": [],
    "Branch_graphrename_1046": [
        [
            "COND",
            "top_iXMIT_load_shiftRegH"
        ],
        [
            "TRUE",
            "PartSelect_graphrename_1047"
        ],
        [
            "FALSE",
            "Branch_graphrename_1050"
        ]
    ],
    "Branch_graphrename_1054": [
        [
            "COND",
            "top_iXMIT_load_shiftRegH"
        ],
        [
            "TRUE",
            "PartSelect_graphrename_1055"
        ],
        [
            "FALSE",
            "Branch_graphrename_1058"
        ]
    ],
    "PartSelect_graphrename_1047": [
        [
            "VAR",
            "top_iXMIT_xmit_dataH"
        ],
        [
            "MSB",
            "'d7_graphrename_1048"
        ],
        [
            "LSB",
            "'d7_graphrename_1049"
        ]
    ],
    "Branch_graphrename_1050": [
        [
            "TRUE",
            "top_iXMIT_xmit_ShiftRegH"
        ],
        [
            "",
            "top.iXMIT.shiftEnaH_graphrename_973"
        ],
        [
            "FALSE",
            "PartSelect_graphrename_1051"
        ]
    ],
    "PartSelect_graphrename_1055": [
        [
            "VAR",
            "top_iXMIT_xmit_dataH"
        ],
        [
            "MSB",
            "'d6_graphrename_1056"
        ],
        [
            "LSB",
            "'d0_graphrename_1057"
        ]
    ],
    "Branch_graphrename_1058": [
        [
            "TRUE",
            "top_iXMIT_xmit_ShiftRegH"
        ],
        [
            "",
            "top.iXMIT.shiftEnaH_graphrename_973"
        ],
        [
            "FALSE",
            "PartSelect_graphrename_1059"
        ]
    ],
    "top_iXMIT_xmit_dataH": [],
    "'d7_graphrename_1048": [],
    "'d7_graphrename_1049": [],
    "PartSelect_graphrename_1051": [
        [
            "VAR",
            "top_iXMIT_xmit_ShiftRegH"
        ],
        [
            "MSB",
            "'d7_graphrename_1052"
        ],
        [
            "LSB",
            "'d7_graphrename_1053"
        ]
    ],
    "'d7_graphrename_1052": [],
    "'d7_graphrename_1053": [],
    "'d6_graphrename_1056": [],
    "'d0_graphrename_1057": [],
    "PartSelect_graphrename_1059": [
        [
            "VAR",
            "top_iXMIT_xmit_ShiftRegH"
        ],
        [
            "MSB",
            "'d6_graphrename_1060"
        ],
        [
            "LSB",
            "'d0_graphrename_1061"
        ]
    ],
    "'d6_graphrename_1060": [],
    "'d0_graphrename_1061": [],
    "Eq_graphrename_1064": [
        [
            "",
            "top.iXMIT.state_graphrename_989"
        ],
        [
            "",
            "3'd0_graphrename_1065"
        ]
    ],
    "Branch_graphrename_1066": [
        [
            "",
            "top.iXMIT.xmitH_graphrename_1146"
        ],
        [
            "TRUE",
            "Concat_graphrename_1067"
        ],
        [
            "FALSE",
            "Concat_graphrename_1070"
        ]
    ],
    "Concat_graphrename_1094": [
        [
            "",
            "1'd1_graphrename_1095"
        ],
        [
            "",
            "PartSelect_graphrename_1096"
        ]
    ],
    "Branch_graphrename_1099": [
        [
            "COND",
            "Eq_graphrename_1100"
        ],
        [
            "TRUE",
            "Concat_graphrename_1102"
        ],
        [
            "FALSE",
            "Concat_graphrename_1129"
        ]
    ],
    "3'd0_graphrename_1065": [],
    "Concat_graphrename_1067": [
        [
            "",
            "1'd0_graphrename_1068"
        ],
        [
            "",
            "7'd0_graphrename_1069"
        ]
    ],
    "Concat_graphrename_1070": [
        [
            "",
            "Branch_graphrename_1071"
        ],
        [
            "",
            "Branch_graphrename_1082"
        ]
    ],
    "1'd0_graphrename_1068": [],
    "7'd0_graphrename_1069": [],
    "Branch_graphrename_1071": [
        [
            "COND",
            "Unot_graphrename_1072"
        ],
        [
            "TRUE",
            "1'd0_graphrename_1073"
        ],
        [
            "FALSE",
            "Branch_graphrename_1074"
        ]
    ],
    "Branch_graphrename_1082": [
        [
            "COND",
            "Unot_graphrename_1083"
        ],
        [
            "TRUE",
            "7'd0_graphrename_1084"
        ],
        [
            "FALSE",
            "Branch_graphrename_1085"
        ]
    ],
    "Unot_graphrename_1072": [
        [
            "",
            "top_iXMIT_sys_rst_l"
        ]
    ],
    "1'd0_graphrename_1073": [],
    "Branch_graphrename_1074": [
        [
            "COND",
            "top_iXMIT_load_shiftRegH"
        ],
        [
            "TRUE",
            "PartSelect_graphrename_1075"
        ],
        [
            "FALSE",
            "Branch_graphrename_1078"
        ]
    ],
    "Unot_graphrename_1083": [
        [
            "",
            "top_iXMIT_sys_rst_l"
        ]
    ],
    "7'd0_graphrename_1084": [],
    "Branch_graphrename_1085": [
        [
            "COND",
            "top_iXMIT_load_shiftRegH"
        ],
        [
            "TRUE",
            "PartSelect_graphrename_1086"
        ],
        [
            "FALSE",
            "Branch_graphrename_1089"
        ]
    ],
    "PartSelect_graphrename_1075": [
        [
            "VAR",
            "top_iXMIT_xmit_dataH"
        ],
        [
            "MSB",
            "'d7_graphrename_1076"
        ],
        [
            "LSB",
            "'d7_graphrename_1077"
        ]
    ],
    "Branch_graphrename_1078": [
        [
            "TRUE",
            "top_iXMIT_xmit_ShiftRegH"
        ],
        [
            "",
            "top.iXMIT.shiftEnaH_graphrename_973"
        ],
        [
            "FALSE",
            "PartSelect_graphrename_1079"
        ]
    ],
    "'d7_graphrename_1076": [],
    "'d7_graphrename_1077": [],
    "PartSelect_graphrename_1079": [
        [
            "VAR",
            "top_iXMIT_xmit_ShiftRegH"
        ],
        [
            "MSB",
            "'d7_graphrename_1080"
        ],
        [
            "LSB",
            "'d7_graphrename_1081"
        ]
    ],
    "'d7_graphrename_1080": [],
    "'d7_graphrename_1081": [],
    "PartSelect_graphrename_1086": [
        [
            "VAR",
            "top_iXMIT_xmit_dataH"
        ],
        [
            "MSB",
            "'d6_graphrename_1087"
        ],
        [
            "LSB",
            "'d0_graphrename_1088"
        ]
    ],
    "Branch_graphrename_1089": [
        [
            "TRUE",
            "top_iXMIT_xmit_ShiftRegH"
        ],
        [
            "",
            "top.iXMIT.shiftEnaH_graphrename_973"
        ],
        [
            "FALSE",
            "PartSelect_graphrename_1090"
        ]
    ],
    "'d6_graphrename_1087": [],
    "'d0_graphrename_1088": [],
    "PartSelect_graphrename_1090": [
        [
            "VAR",
            "top_iXMIT_xmit_ShiftRegH"
        ],
        [
            "MSB",
            "'d6_graphrename_1091"
        ],
        [
            "LSB",
            "'d0_graphrename_1092"
        ]
    ],
    "'d6_graphrename_1091": [],
    "'d0_graphrename_1092": [],
    "1'd1_graphrename_1095": [],
    "PartSelect_graphrename_1096": [
        [
            "VAR",
            "top_iXMIT_xmit_ShiftRegH"
        ],
        [
            "MSB",
            "'d7_graphrename_1097"
        ],
        [
            "LSB",
            "'d1_graphrename_1098"
        ]
    ],
    "Eq_graphrename_1100": [
        [
            "",
            "top.iXMIT.state_graphrename_989"
        ],
        [
            "",
            "3'd0_graphrename_1101"
        ]
    ],
    "Concat_graphrename_1102": [
        [
            "",
            "Branch_graphrename_1103"
        ],
        [
            "",
            "Branch_graphrename_1116"
        ]
    ],
    "Concat_graphrename_1129": [
        [
            "",
            "top_iXMIT_xmit_ShiftRegH"
        ]
    ],
    "'d7_graphrename_1097": [],
    "'d1_graphrename_1098": [],
    "3'd0_graphrename_1101": [],
    "Branch_graphrename_1103": [
        [
            "",
            "top.iXMIT.xmitH_graphrename_1146"
        ],
        [
            "TRUE",
            "1'd0_graphrename_1104"
        ],
        [
            "FALSE",
            "Branch_graphrename_1105"
        ]
    ],
    "Branch_graphrename_1116": [
        [
            "",
            "top.iXMIT.xmitH_graphrename_1146"
        ],
        [
            "TRUE",
            "7'd0_graphrename_1117"
        ],
        [
            "FALSE",
            "Branch_graphrename_1118"
        ]
    ],
    "1'd0_graphrename_1104": [],
    "Branch_graphrename_1105": [
        [
            "COND",
            "Unot_graphrename_1106"
        ],
        [
            "TRUE",
            "1'd0_graphrename_1107"
        ],
        [
            "FALSE",
            "Branch_graphrename_1108"
        ]
    ],
    "7'd0_graphrename_1117": [],
    "Branch_graphrename_1118": [
        [
            "COND",
            "Unot_graphrename_1119"
        ],
        [
            "TRUE",
            "7'd0_graphrename_1120"
        ],
        [
            "FALSE",
            "Branch_graphrename_1121"
        ]
    ],
    "Unot_graphrename_1106": [
        [
            "",
            "top_iXMIT_sys_rst_l"
        ]
    ],
    "1'd0_graphrename_1107": [],
    "Branch_graphrename_1108": [
        [
            "COND",
            "top_iXMIT_load_shiftRegH"
        ],
        [
            "TRUE",
            "PartSelect_graphrename_1109"
        ],
        [
            "FALSE",
            "Branch_graphrename_1112"
        ]
    ],
    "PartSelect_graphrename_1109": [
        [
            "VAR",
            "top_iXMIT_xmit_dataH"
        ],
        [
            "MSB",
            "'d7_graphrename_1110"
        ],
        [
            "LSB",
            "'d7_graphrename_1111"
        ]
    ],
    "Branch_graphrename_1112": [
        [
            "TRUE",
            "top_iXMIT_xmit_ShiftRegH"
        ],
        [
            "",
            "top.iXMIT.shiftEnaH_graphrename_973"
        ],
        [
            "FALSE",
            "PartSelect_graphrename_1113"
        ]
    ],
    "'d7_graphrename_1110": [],
    "'d7_graphrename_1111": [],
    "PartSelect_graphrename_1113": [
        [
            "VAR",
            "top_iXMIT_xmit_ShiftRegH"
        ],
        [
            "MSB",
            "'d7_graphrename_1114"
        ],
        [
            "LSB",
            "'d7_graphrename_1115"
        ]
    ],
    "'d7_graphrename_1114": [],
    "'d7_graphrename_1115": [],
    "Unot_graphrename_1119": [
        [
            "",
            "top_iXMIT_sys_rst_l"
        ]
    ],
    "7'd0_graphrename_1120": [],
    "Branch_graphrename_1121": [
        [
            "COND",
            "top_iXMIT_load_shiftRegH"
        ],
        [
            "TRUE",
            "PartSelect_graphrename_1122"
        ],
        [
            "FALSE",
            "Branch_graphrename_1125"
        ]
    ],
    "PartSelect_graphrename_1122": [
        [
            "VAR",
            "top_iXMIT_xmit_dataH"
        ],
        [
            "MSB",
            "'d6_graphrename_1123"
        ],
        [
            "LSB",
            "'d0_graphrename_1124"
        ]
    ],
    "Branch_graphrename_1125": [
        [
            "TRUE",
            "top_iXMIT_xmit_ShiftRegH"
        ],
        [
            "",
            "top.iXMIT.shiftEnaH_graphrename_973"
        ],
        [
            "FALSE",
            "PartSelect_graphrename_1126"
        ]
    ],
    "'d6_graphrename_1123": [],
    "'d0_graphrename_1124": [],
    "PartSelect_graphrename_1126": [
        [
            "VAR",
            "top_iXMIT_xmit_ShiftRegH"
        ],
        [
            "MSB",
            "'d6_graphrename_1127"
        ],
        [
            "LSB",
            "'d0_graphrename_1128"
        ]
    ],
    "'d6_graphrename_1127": [],
    "'d0_graphrename_1128": [],
    "Eq_graphrename_1132": [
        [
            "",
            "top.iXMIT.state_graphrename_989"
        ],
        [
            "",
            "3'd0_graphrename_1133"
        ]
    ],
    "Branch_graphrename_1134": [
        [
            "COND",
            "Eq_graphrename_1135"
        ],
        [
            "TRUE",
            "top_iXMIT__rn17_xmitDataSelH"
        ],
        [
            "FALSE",
            "Branch_graphrename_1137"
        ]
    ],
    "3'd0_graphrename_1133": [],
    "Eq_graphrename_1135": [
        [
            "",
            "top.iXMIT.state_graphrename_989"
        ],
        [
            "",
            "3'd2_graphrename_1136"
        ]
    ],
    "top_iXMIT__rn17_xmitDataSelH": [],
    "Branch_graphrename_1137": [
        [
            "COND",
            "Eq_graphrename_1138"
        ],
        [
            "TRUE",
            "top_iXMIT__rn21_xmitDataSelH"
        ],
        [
            "FALSE",
            "Branch_graphrename_1140"
        ]
    ],
    "3'd2_graphrename_1136": [],
    "Eq_graphrename_1138": [
        [
            "",
            "top.iXMIT.state_graphrename_989"
        ],
        [
            "",
            "3'd3_graphrename_1139"
        ]
    ],
    "top_iXMIT__rn21_xmitDataSelH": [],
    "Branch_graphrename_1140": [
        [
            "COND",
            "Eq_graphrename_1141"
        ],
        [
            "TRUE",
            "top_iXMIT__rn27_xmitDataSelH"
        ],
        [
            "FALSE",
            "Branch_graphrename_1143"
        ]
    ],
    "3'd3_graphrename_1139": [],
    "Eq_graphrename_1141": [
        [
            "",
            "top.iXMIT.state_graphrename_989"
        ],
        [
            "",
            "3'd4_graphrename_1142"
        ]
    ],
    "top_iXMIT__rn27_xmitDataSelH": [],
    "Branch_graphrename_1143": [
        [
            "FALSE",
            "top_iXMIT__rn41_xmitDataSelH"
        ],
        [
            "COND",
            "Eq_graphrename_1144"
        ],
        [
            "TRUE",
            "top_iXMIT__rn30_xmitDataSelH"
        ]
    ],
    "3'd4_graphrename_1142": [],
    "Eq_graphrename_1144": [
        [
            "",
            "top.iXMIT.state_graphrename_989"
        ],
        [
            "",
            "3'd5_graphrename_1145"
        ]
    ],
    "top_iXMIT__rn30_xmitDataSelH": [],
    "3'd5_graphrename_1145": [],
    "top.rec_dataH_graphrename_1147": [
        [
            "",
            "Branch_graphrename_1148"
        ]
    ],
    "Branch_graphrename_1148": [
        [
            "COND",
            "Unot_graphrename_1149"
        ],
        [
            "TRUE",
            "top__rn60_rec_dataH"
        ],
        [
            "FALSE",
            "top__rn61_rec_dataH"
        ]
    ],
    "Unot_graphrename_1149": [
        [
            "",
            "top_sys_rst_l"
        ]
    ],
    "top__rn60_rec_dataH": [],
    "top__rn61_rec_dataH": [],
    "top.rec_dataH_rec_graphrename_1150": [
        [
            "",
            "top_iRECEIVER_rec_dataH"
        ]
    ],
    "top_iRECEIVER_rec_dataH": [],
    "top.rec_dataH_temp_graphrename_1151": [
        [
            "",
            "Branch_graphrename_1152"
        ]
    ],
    "Branch_graphrename_1152": [
        [
            "COND",
            "Unot_graphrename_1153"
        ],
        [
            "TRUE",
            "1'd0_graphrename_1154"
        ],
        [
            "FALSE",
            "top_rec_dataH_rec"
        ]
    ],
    "Unot_graphrename_1153": [
        [
            "",
            "top_sys_rst_l"
        ]
    ],
    "1'd0_graphrename_1154": [],
    "top_rec_dataH_rec": [],
    "top.rec_readyH_graphrename_1155": [
        [
            "",
            "top_iRECEIVER_rec_readyH"
        ]
    ],
    "top_iRECEIVER_rec_readyH": [],
    "top.uart_XMIT_dataH_graphrename_1156": [
        [
            "",
            "top_iXMIT_uart_xmitH"
        ]
    ],
    "top_iXMIT_uart_xmitH": [],
    "top.xmit_doneH_graphrename_1157": [
        [
            "",
            "top_iXMIT_xmit_doneH"
        ]
    ],
    "top_iXMIT_xmit_doneH": []
}